sregex/__init__.py
sregex-0.1.dist-info/METADATA
sregex-0.1.dist-info/WHEEL
sregex-0.1.dist-info/top_level.txt
sregex-0.1.dist-info/RECORD
